asteroid_sphinx_theme.py
asteroid_sphinx_theme/__init__.py
asteroid_sphinx_theme/breadcrumbs.html
asteroid_sphinx_theme/cookie_banner.html
asteroid_sphinx_theme/fonts.html
asteroid_sphinx_theme/footer.html
asteroid_sphinx_theme/layout.html
asteroid_sphinx_theme/search.html
asteroid_sphinx_theme/searchbox.html
asteroid_sphinx_theme/theme.conf
asteroid_sphinx_theme/theme_variables.jinja
asteroid_sphinx_theme/versions.html
asteroid_sphinx_theme/static/css/theme.css
asteroid_sphinx_theme/static/css/theme.css.map
asteroid_sphinx_theme/static/fonts/FreightSans/freight-sans-bold-italic.woff
asteroid_sphinx_theme/static/fonts/FreightSans/freight-sans-bold-italic.woff2
asteroid_sphinx_theme/static/fonts/FreightSans/freight-sans-bold.woff
asteroid_sphinx_theme/static/fonts/FreightSans/freight-sans-bold.woff2
asteroid_sphinx_theme/static/fonts/FreightSans/freight-sans-book-italic.woff
asteroid_sphinx_theme/static/fonts/FreightSans/freight-sans-book-italic.woff2
asteroid_sphinx_theme/static/fonts/FreightSans/freight-sans-book.woff
asteroid_sphinx_theme/static/fonts/FreightSans/freight-sans-book.woff2
asteroid_sphinx_theme/static/fonts/FreightSans/freight-sans-light-italic.woff
asteroid_sphinx_theme/static/fonts/FreightSans/freight-sans-light-italic.woff2
asteroid_sphinx_theme/static/fonts/FreightSans/freight-sans-light.woff
asteroid_sphinx_theme/static/fonts/FreightSans/freight-sans-light.woff2
asteroid_sphinx_theme/static/fonts/FreightSans/freight-sans-medium-italic.woff
asteroid_sphinx_theme/static/fonts/FreightSans/freight-sans-medium-italic.woff2
asteroid_sphinx_theme/static/fonts/FreightSans/freight-sans-medium.woff
asteroid_sphinx_theme/static/fonts/FreightSans/freight-sans-medium.woff2
asteroid_sphinx_theme/static/fonts/IBMPlexMono/IBMPlexMono-Light.woff
asteroid_sphinx_theme/static/fonts/IBMPlexMono/IBMPlexMono-Light.woff2
asteroid_sphinx_theme/static/fonts/IBMPlexMono/IBMPlexMono-Medium.woff
asteroid_sphinx_theme/static/fonts/IBMPlexMono/IBMPlexMono-Medium.woff2
asteroid_sphinx_theme-0.0.3.dist-info/LICENSE
asteroid_sphinx_theme-0.0.3.dist-info/METADATA
asteroid_sphinx_theme-0.0.3.dist-info/WHEEL
asteroid_sphinx_theme-0.0.3.dist-info/entry_points.txt
asteroid_sphinx_theme-0.0.3.dist-info/top_level.txt
asteroid_sphinx_theme-0.0.3.dist-info/RECORD
