Metadata-Version: 2.1
Name: asteroid-sphinx-theme
Version: 0.0.3
Summary: Asteroid: Sphinx Theme
Home-page: https://github.com/pytorch/lightning_sphinx_theme
Author: Asteroid
Author-email: asteroid@asteroid.com
License: MIT License
Platform: UNKNOWN
Classifier: Development Status :: 5 - Production/Stable
Classifier: Environment :: Web Environment
Classifier: Intended Audience :: Developers
Classifier: Intended Audience :: System Administrators
Classifier: License :: OSI Approved :: MIT License
Classifier: Operating System :: OS Independent
Classifier: Programming Language :: Python
Classifier: Topic :: Internet
Classifier: Topic :: Software Development :: Documentation
Requires-Dist: sphinx
